LICENSE
MANIFEST.in
README.rst
VERSION
requirements-dev.txt
requirements.txt
setup.cfg
setup.py
molo/__init__.py
molo.polls.egg-info/PKG-INFO
molo.polls.egg-info/SOURCES.txt
molo.polls.egg-info/dependency_links.txt
molo.polls.egg-info/namespace_packages.txt
molo.polls.egg-info/not-zip-safe
molo.polls.egg-info/requires.txt
molo.polls.egg-info/top_level.txt
molo/polls/__init__.py
molo/polls/admin.py
molo/polls/admin_views.py
molo/polls/forms.py
molo/polls/models.py
molo/polls/urls.py
molo/polls/views.py
molo/polls/wagtail_hooks.py
molo/polls/migrations/0001_initial.py
molo/polls/migrations/0002_pollsindexpage.py
molo/polls/migrations/0003_create_polls_index_pages.py
molo/polls/migrations/0004_add-polls-permissions-to-groups.py
molo/polls/migrations/0005_add_translation_fields.py
molo/polls/migrations/__init__.py
molo/polls/templates/admin/question_results.html
molo/polls/templates/polls/detail.html
molo/polls/templates/polls/free_text_detail.html
molo/polls/templates/polls/free_text_question.html
molo/polls/templates/polls/poll_page.html
molo/polls/templates/polls/poll_page_in_section.html
molo/polls/templates/polls/polls_details.html
molo/polls/templates/polls/question.html
molo/polls/templates/polls/results.html
molo/polls/templates/polls/includes/poll_free_text_form.html
molo/polls/templates/polls/includes/poll_question_form.html
molo/polls/templatetags/__init__.py
molo/polls/templatetags/poll_votings.py
molo/polls/test_templates/base.html
molo/polls/test_templates/main.html
molo/polls/test_templates/section_page.html
molo/polls/tests/__init__.py
molo/polls/tests/base.py
molo/polls/tests/test_admin.py
molo/polls/tests/test_models.py
molo/polls/tests/test_templatetags.py
molo/polls/tests/test_translation.py
molo/polls/tests/test_views.py
molo/polls/tests/test_voting.py
molo/polls/tests/test_wagtail_admin.py