Metadata-Version: 1.1
Name: molo.polls
Version: 8.1.0
Summary: A molo module that provides the ability to run polls.
Home-page: http://github.com/praekelt/molo.polls
Author: Praekelt Foundation
Author-email: dev@praekelt.com
License: BSD
Keywords: praekelt,mobi,web,django
Platform: UNKNOWN
Classifier: Programming Language :: Python :: 3.6
Classifier: Framework :: Django
Classifier: Topic :: Internet :: WWW/HTTP
Classifier: Topic :: Internet :: WWW/HTTP :: WSGI :: Application
